sfam/__init__.py
sfam/data/__init__.py
sfam/data/gesture_loader.py
sfam/data/synthetic_data.py
sfam/eval/__init__.py
sfam/eval/evaluate.py
sfam/modalities/__init__.py
sfam/modalities/gesture_fm.py
sfam/modalities/image_fm.py
sfam/modalities/text_fm.py
sfam/models/__init__.py
sfam/models/abstraction.py
sfam/models/encoders.py
sfam/models/sfam_adaptive.py
sfam/models/sfam_net.py
sfam/training/__init__.py
sfam/training/losses.py
sfam/training/train.py
sfam_adr-1.2.6.dist-info/METADATA
sfam_adr-1.2.6.dist-info/WHEEL
sfam_adr-1.2.6.dist-info/top_level.txt
sfam_adr-1.2.6.dist-info/RECORD
