Metadata-Version: 2.4
Name: sfam-ADR
Version: 1.2.6
Summary: A neuro-symbolic, privacy-preserving biometric authentication engine.
Home-page: https://github.com/Lumine8/SFAM
Author: lumine8
Requires-Python: >=3.8
Requires-Dist: torch>=2.0.0
Requires-Dist: numpy
Requires-Dist: timm
Requires-Dist: pillow
Requires-Dist: torchvision
Requires-Dist: opencv-python
Requires-Dist: fastapi
Requires-Dist: uvicorn
Requires-Dist: pydantic
Dynamic: author
Dynamic: description
Dynamic: description-content-type
Dynamic: home-page
Dynamic: requires-dist
Dynamic: requires-python
Dynamic: summary
